tf_notification_callback/__init__.py
tf_notification_callback/main.py
tf_notification_callback-0.2.dist-info/METADATA
tf_notification_callback-0.2.dist-info/WHEEL
tf_notification_callback-0.2.dist-info/top_level.txt
tf_notification_callback-0.2.dist-info/RECORD
