Metadata-Version: 2.1
Name: tf-notification-callback
Version: 0.2
Summary: Receive notifications about your model training anywhere you want!
Home-page: https://github.com/techytushar/tf_notification_callback
Author: Tushar Mittal
Author-email: chiragmittal.mittal@gmail.com
License: GNU General Public License v3 (GPLv3)
Keywords: api python keras training callback tensorflow machine learning deep learning nlp
Platform: UNKNOWN
Classifier: Development Status :: 4 - Beta
Classifier: Intended Audience :: Developers
Classifier: License :: OSI Approved :: GNU General Public License v3 (GPLv3)
Classifier: Programming Language :: Python :: 3
Requires-Python: >=3.6
Requires-Dist: python-telegram-bot (>=12)
Requires-Dist: matplotlib (>=3)
Requires-Dist: keras (>=2.3)
Requires-Dist: tensorflow (>=2)
